sshgateway.py
sshgateway-0.1.4.dist-info/DESCRIPTION.rst
sshgateway-0.1.4.dist-info/METADATA
sshgateway-0.1.4.dist-info/RECORD
sshgateway-0.1.4.dist-info/WHEEL
sshgateway-0.1.4.dist-info/entry_points.txt
sshgateway-0.1.4.dist-info/metadata.json
sshgateway-0.1.4.dist-info/top_level.txt
