Metadata-Version: 2.0
Name: sshgateway
Version: 0.1.4
Summary: A ssh gateway server
Home-page: https://github.com/guyingbo/sshgateway
Author: Yingbo Gu
Author-email: tensiongyb@gmail.com
License: MIT
Platform: UNKNOWN
Classifier: Programming Language :: Python :: 3.6
Requires-Dist: asyncssh (>=1.10.1)
Requires-Dist: pytoml (>=0.1.14)
